{"skeleton":{"width":200,"height":300,"fps":24,"hash":" ","name":"Armature"},"bones":[{"name":"root"},{"length":159,"x":-18,"y":52,"rotation":89.6397,"name":"Alice","parent":"root"},{"length":144,"x":13.1331,"y":26.5831,"rotation":-88.7899,"name":"Crowbar","parent":"Alice"}],"slots":[{"name":"Alice","bone":"Alice","attachment":"Alice"},{"name":"Crowbar","bone":"Crowbar"},{"name":"supernova","bone":"Crowbar"},{"name":"woodenstick","bone":"Crowbar"},{"name":"sword","bone":"Crowbar"},{"name":"rogue","bone":"Crowbar"},{"name":"WizardHat","bone":"Crowbar"}],"skins":{"default":{"woodenstick":{"woodenstick":{"name":"woodenstick","width":200,"height":200,"x":110.97,"y":16.82,"rotation":-0.85,"scaleX":0.3812,"scaleY":0.3812}},"sword":{"sword":{"name":"sword","width":218,"height":125,"x":113.9,"y":32.6,"rotation":-0.85}},"rogue":{"rogue":{"name":"rogue","width":200,"height":300,"x":37.01,"y":57.59,"rotation":-0.85}},"WizardHat":{"WizardHat":{"name":"WizardHat","width":160,"height":121,"x":29.31,"y":147.17,"rotation":-0.85}},"Alice":{"Alice":{"name":"Alice","width":200,"height":300,"x":71.06,"y":-9.55,"rotation":-89.64},"idol":{"name":"idol","width":200,"height":300,"x":71.06,"y":-9.55,"rotation":-89.64}},"Crowbar":{"Crowbar":{"name":"Crowbar","width":218,"height":125,"x":49.82,"y":20.96,"rotation":-0.85}},"supernova":{"supernova":{"name":"supernova","width":800,"height":380,"x":37.08,"y":-12.25,"rotation":-0.85,"scaleX":0.3551,"scaleY":0.3551}}}},"animations":{"baseAnimation":{"bones":{"Alice":{"scale":[{"time":0,"curve":[0,0,0.5,1],"x":1,"y":1},{"time":0.8333,"curve":[0.5,0,1,1],"x":0.96,"y":1},{"time":1.6666,"x":1,"y":1}]}}},"baseAnimation_AOEDPS":{"bones":{"Alice":{"scale":[{"time":0,"curve":[0,0,0.5,1],"x":1,"y":1},{"time":0.8333,"curve":[0.5,0,1,1],"x":0.96,"y":1},{"time":1.6666,"x":1,"y":1}]}},"slots":{"supernova":{"attachment":[{"time":0,"name":"supernova"}]}}},"baseAnimation_Warrior":{"bones":{"Alice":{"scale":[{"time":0,"curve":[0,0,0.5,1],"x":1,"y":1},{"time":0.8333,"curve":[0.5,0,1,1],"x":0.96,"y":1},{"time":1.6666,"x":1,"y":1}]}},"slots":{"Crowbar":{"attachment":[{"time":0,"name":"Crowbar"}]}}},"baseAnimation_Newby":{"bones":{"Alice":{"scale":[{"time":0,"curve":[0,0,0.5,1],"x":1,"y":1},{"time":0.8333,"curve":[0.5,0,1,1],"x":0.96,"y":1},{"time":1.6666,"x":1,"y":1}]}},"slots":{"woodenstick":{"attachment":[{"time":0,"name":"woodenstick"}]}}},"baseAnimation_Hero":{"bones":{"Alice":{"scale":[{"time":0,"curve":[0,0,0.5,1],"x":1,"y":1},{"time":0.8333,"curve":[0.5,0,1,1],"x":0.96,"y":1},{"time":1.6666,"x":1,"y":1}]}},"slots":{"sword":{"attachment":[{"time":0,"name":"sword"}]}}},"baseAnimation_Idol":{"bones":{"Alice":{"scale":[{"time":0,"curve":[0,0,0.5,1],"x":1,"y":1},{"time":0.8333,"curve":[0.5,0,1,1],"x":0.96,"y":1},{"time":1.6666,"x":1,"y":1}]}},"slots":{"Alice":{"attachment":[{"time":0,"name":"idol"}]}}},"baseAnimation_Rogue":{"bones":{"Alice":{"scale":[{"time":0,"curve":[0,0,0.5,1],"x":1,"y":1},{"time":0.8333,"curve":[0.5,0,1,1],"x":0.96,"y":1},{"time":1.6666,"x":1,"y":1}]}},"slots":{"rogue":{"attachment":[{"time":0,"name":"rogue"}]}}},"baseAnimation_Wizard":{"bones":{"Alice":{"scale":[{"time":0,"curve":[0,0,0.5,1],"x":1,"y":1},{"time":0.8333,"curve":[0.5,0,1,1],"x":0.96,"y":1},{"time":1.6666,"x":1,"y":1}]}},"slots":{"WizardHat":{"attachment":[{"time":0,"name":"WizardHat"}]}}}}}